vibeflip/__init__.py
vibeflip/vibeflip.py
vibeflip-0.1.0.dist-info/METADATA
vibeflip-0.1.0.dist-info/WHEEL
vibeflip-0.1.0.dist-info/licenses/LICENSE
vibeflip-0.1.0.dist-info/RECORD
