Metadata-Version: 2.4
Name: vibeflip
Version: 0.1.0
Summary: Coin flip library that uses GPT for true randomness
Author-email: Max Scheijen <maxscheijen@protonmail.com>
License-File: LICENSE
Requires-Python: >=3.10
Requires-Dist: openai>=1.102.0
Requires-Dist: pydantic>=2.11.7
